ttconv/__init__.py
ttconv/config.py
ttconv/isd.py
ttconv/model.py
ttconv/style_properties.py
ttconv/time_code.py
ttconv/tt.py
ttconv/utils.py
ttconv/filters/__init__.py
ttconv/filters/document_filter.py
ttconv/filters/isd_filter.py
ttconv/filters/remove_animations.py
ttconv/filters/supported_style_properties.py
ttconv/filters/doc/__init__.py
ttconv/filters/doc/lcd.py
ttconv/filters/isd/__init__.py
ttconv/filters/isd/default_style_properties.py
ttconv/filters/isd/merge_paragraphs.py
ttconv/filters/isd/merge_regions.py
ttconv/filters/isd/supported_style_properties.py
ttconv/imsc/__init__.py
ttconv/imsc/attributes.py
ttconv/imsc/config.py
ttconv/imsc/designators.py
ttconv/imsc/elements.py
ttconv/imsc/namespaces.py
ttconv/imsc/reader.py
ttconv/imsc/style_properties.py
ttconv/imsc/utils.py
ttconv/imsc/writer.py
ttconv/scc/__init__.py
ttconv/scc/caption_line.py
ttconv/scc/caption_paragraph.py
ttconv/scc/caption_style.py
ttconv/scc/caption_text.py
ttconv/scc/config.py
ttconv/scc/context.py
ttconv/scc/disassembly.py
ttconv/scc/dump.py
ttconv/scc/line.py
ttconv/scc/reader.py
ttconv/scc/utils.py
ttconv/scc/word.py
ttconv/scc/writer.py
ttconv/scc/codes/__init__.py
ttconv/scc/codes/attribute_codes.py
ttconv/scc/codes/characters.py
ttconv/scc/codes/control_codes.py
ttconv/scc/codes/extended_characters.py
ttconv/scc/codes/mid_row_codes.py
ttconv/scc/codes/preambles_address_codes.py
ttconv/scc/codes/special_characters.py
ttconv/scc/codes/standard_characters.py
ttconv/srt/__init__.py
ttconv/srt/config.py
ttconv/srt/paragraph.py
ttconv/srt/reader.py
ttconv/srt/style.py
ttconv/srt/writer.py
ttconv/stl/__init__.py
ttconv/stl/config.py
ttconv/stl/datafile.py
ttconv/stl/iso6937.py
ttconv/stl/reader.py
ttconv/stl/tf.py
ttconv/vtt/__init__.py
ttconv/vtt/config.py
ttconv/vtt/css_class.py
ttconv/vtt/cue.py
ttconv/vtt/reader.py
ttconv/vtt/style.py
ttconv/vtt/tokenizer.py
ttconv/vtt/writer.py
ttconv-1.2.1.dist-info/licenses/LICENSE.txt
ttconv-1.2.1.dist-info/METADATA
ttconv-1.2.1.dist-info/WHEEL
ttconv-1.2.1.dist-info/entry_points.txt
ttconv-1.2.1.dist-info/top_level.txt
ttconv-1.2.1.dist-info/RECORD
