Metadata-Version: 2.4
Name: ttconv
Version: 1.2.1
Summary: Library for conversion of common timed text formats
Home-page: https://github.com/sandflow/ttconv
Author: Sandflow Consulting LLC
Author-email: info@sandflow.com
Project-URL: Bug Reports, https://github.com/sandflow/ttconv/issues
Project-URL: Source, https://github.com/sandflow/ttconv
Keywords: ttml,timed text,caption,subtitle,imsc,scc,srt,stl,smpte-tt,conversion,vtt,webvtt,608
Classifier: Development Status :: 5 - Production/Stable
Classifier: Intended Audience :: Developers
Classifier: Topic :: Software Development :: Build Tools
Classifier: Environment :: Console
Classifier: License :: OSI Approved :: BSD License
Classifier: Programming Language :: Python :: 3.7
Classifier: Programming Language :: Python :: 3.8
Classifier: Programming Language :: Python :: 3 :: Only
Classifier: Topic :: Multimedia
Requires-Python: >=3.7, <4
License-File: LICENSE.txt
Dynamic: author
Dynamic: author-email
Dynamic: classifier
Dynamic: description
Dynamic: description-content-type
Dynamic: home-page
Dynamic: keywords
Dynamic: license-file
Dynamic: project-url
Dynamic: requires-python
Dynamic: summary
